README.md
setup.py
otools/__init__.py
otools/macros.py
otools.egg-info/PKG-INFO
otools.egg-info/SOURCES.txt
otools.egg-info/dependency_links.txt
otools.egg-info/requires.txt
otools.egg-info/top_level.txt
otools/core/Context.py
otools/core/Dataframe.py
otools/core/OTools.py
otools/core/Service.py
otools/core/Swarm.py
otools/core/Trigger.py
otools/core/TriggerCondition.py
otools/core/Watchdog.py
otools/core/__init__.py
otools/exceptions/FatalError.py
otools/exceptions/__init__.py
otools/logging/Logger.py
otools/logging/LoggingLevel.py
otools/logging/__init__.py
otools/status/StatusCode.py
otools/status/__init__.py