Metadata-Version: 2.1
Name: otools
Version: 0.2.2
Summary: OTools stands for Online Tools, which is a Cython/Python framework for developing multithread online systems in a simple way.
Home-page: https://github.com/gabriel-milan/otools
Author: Gabriel Gazola Milan
Author-email: gabriel.gazola@poli.ufrj.br
License: GPL-3.0
Keywords: framework,threading,shared resources,flexibility,python,online
Platform: UNKNOWN
Classifier: Development Status :: 4 - Beta
Classifier: Intended Audience :: Developers
Classifier: Topic :: Software Development :: Libraries :: Python Modules
Classifier: License :: OSI Approved :: GNU General Public License v3 (GPLv3)
Classifier: Programming Language :: Python :: 3
Classifier: Programming Language :: Python :: 3.4
Classifier: Programming Language :: Python :: 3.5
Classifier: Programming Language :: Python :: 3.6
Classifier: Programming Language :: Python :: 3.7
Classifier: Programming Language :: Python :: 3.8
